northgravity/Authenticator.py
northgravity/DatalakeHandler.py
northgravity/ExceptionHandler.py
northgravity/HTTPCalller.py
northgravity/StatusHandler.py
northgravity/TaskHandler.py
northgravity/Timeseries.py
northgravity/__init__.py
northgravity/constants.py
northgravity-0.1.14.dist-info/LICENSE
northgravity-0.1.14.dist-info/METADATA
northgravity-0.1.14.dist-info/WHEEL
northgravity-0.1.14.dist-info/top_level.txt
northgravity-0.1.14.dist-info/RECORD
