Metadata-Version: 2.1
Name: northgravity
Version: 0.1.14
Summary: Python SDK for NorthGravity platform
Home-page: https://www.northgravity.com/
Author: NorthGravity
Author-email: info@northgravity.com
Classifier: Programming Language :: Python :: 3
Classifier: License :: OSI Approved :: MIT License
Classifier: Operating System :: OS Independent
Requires-Python: >=3.6
License-File: LICENSE
Requires-Dist: requests >=2.27.1
Requires-Dist: urllib3 >=1.26.9
